{
  "updatedAt": "2026-02-25T23:04:28.510357+00:00",
  "markets": [
    {
      "segment": "evm",
      "protocol": "aave",
      "chain": "ethereum",
      "chainId": 1,
      "market": "0x87870Bca3F3fD6335C3F4ce8392D69350B4fA4E2",
      "symbol": "USDe",
      "underlyingToken": "0x4c9EDD5852cd905f086C759E8383e09bff1E68B3",
      "supplyApy": 0.008905877182590333,
      "borrowApy": 0.026608329786745995,
      "utilization": 0.4501800069663135,
      "tvlUsd": 1084268854.1554644,
      "isStable": true,
      "isEthereum": true
    },
    {
      "segment": "evm",
      "protocol": "aave",
      "chain": "ethereum",
      "chainId": 1,
      "market": "0x87870Bca3F3fD6335C3F4ce8392D69350B4fA4E2",
      "symbol": "PYUSD",
      "underlyingToken": "0x6c3ea9036406852006290770BEdFcAbA0e23A0e8",
      "supplyApy": 0.016464432148838436,
      "borrowApy": 0.032259157936790496,
      "utilization": 0.5714956447285782,
      "tvlUsd": 446953886.71253055,
      "isStable": true,
      "isEthereum": true
    },
    {
      "segment": "evm",
      "protocol": "aave",
      "chain": "ethereum",
      "chainId": 1,
      "market": "0x87870Bca3F3fD6335C3F4ce8392D69350B4fA4E2",
      "symbol": "USDT",
      "underlyingToken": "0xdAC17F958D2ee523a2206206994597C13D831ec7",
      "supplyApy": 0.018507478377447043,
      "borrowApy": 0.03383731446224794,
      "utilization": 0.6123045249010023,
      "tvlUsd": 5705547268.475121,
      "isStable": true,
      "isEthereum": true
    },
    {
      "segment": "evm",
      "protocol": "aave",
      "chain": "ethereum",
      "chainId": 1,
      "market": "0x87870Bca3F3fD6335C3F4ce8392D69350B4fA4E2",
      "symbol": "RLUSD",
      "underlyingToken": "0x8292Bb45bf1Ee4d140127049757C2E0fF06317eD",
      "supplyApy": 0.008785271175877922,
      "borrowApy": 0.03542736567043502,
      "utilization": 0.3140564956180105,
      "tvlUsd": 611993602.6428778,
      "isStable": true,
      "isEthereum": true
    },
    {
      "segment": "evm",
      "protocol": "aave",
      "chain": "ethereum",
      "chainId": 1,
      "market": "0x87870Bca3F3fD6335C3F4ce8392D69350B4fA4E2",
      "symbol": "USDC",
      "underlyingToken": "0xA0b86991c6218b36c1d19D4a2e9Eb0cE3606eB48",
      "supplyApy": 0.020436081181472568,
      "borrowApy": 0.0355699425672303,
      "utilization": 0.6431147206497592,
      "tvlUsd": 3899302987.3686976,
      "isStable": true,
      "isEthereum": true
    },
    {
      "segment": "evm",
      "protocol": "aave",
      "chain": "ethereum",
      "chainId": 1,
      "market": "0x87870Bca3F3fD6335C3F4ce8392D69350B4fA4E2",
      "symbol": "USDG",
      "underlyingToken": "0xe343167631d89B6Ffc58B88d6b7fB0228795491D",
      "supplyApy": 0.0875493761628957,
      "borrowApy": 0.135294119844672,
      "utilization": 0.8267568975657316,
      "tvlUsd": 50744967.997312,
      "isStable": true,
      "isEthereum": true
    },
    {
      "segment": "evm",
      "protocol": "aave",
      "chain": "arbitrum",
      "chainId": 42161,
      "market": "0x794a61358D6845594F94dc1DB02A252b5b4814aD",
      "symbol": "USDC",
      "underlyingToken": "0xaf88d065e77c8cC2239327C5EDb3A432268e5831",
      "supplyApy": 0.016270160681173967,
      "borrowApy": 0.03206683219430577,
      "utilization": 0.5681415707071555,
      "tvlUsd": 282736440.9418653,
      "isStable": true,
      "isEthereum": false
    },
    {
      "segment": "evm",
      "protocol": "aave",
      "chain": "base",
      "chainId": 8453,
      "market": "0xA238Dd80C259a72e81d7e4664a9801593F98d1c5",
      "symbol": "USDC",
      "underlyingToken": "0x833589fCD6eDb6E08f4c7C32D4f71b54bdA02913",
      "supplyApy": 0.03454853644372972,
      "borrowApy": 0.046853283258931386,
      "utilization": 0.8241977840419952,
      "tvlUsd": 392206231.4441066,
      "isStable": true,
      "isEthereum": false
    },
    {
      "segment": "evm",
      "protocol": "aave",
      "chain": "ethereum",
      "chainId": 1,
      "market": "0x87870Bca3F3fD6335C3F4ce8392D69350B4fA4E2",
      "symbol": "EURC",
      "underlyingToken": "0x1aBaEA1f7C830bD89Acc67eC4af516284b1bC33c",
      "supplyApy": 0.023084549177820872,
      "borrowApy": 0.04015069933346253,
      "utilization": 0.6441645022935222,
      "tvlUsd": 95040692.6544591,
      "isStable": false,
      "isEthereum": true
    },
    {
      "segment": "evm",
      "protocol": "aave",
      "chain": "ethereum",
      "chainId": 1,
      "market": "0x87870Bca3F3fD6335C3F4ce8392D69350B4fA4E2",
      "symbol": "WETH",
      "underlyingToken": "0xC02aaA39b223FE8D0A0e5C4F27eAD9083C756Cc2",
      "supplyApy": 0.022100193217789187,
      "borrowApy": 0.027653513914569734,
      "utilization": 0.9427780691133955,
      "tvlUsd": 6044906156.713427,
      "isStable": false,
      "isEthereum": true
    },
    {
      "segment": "evm",
      "protocol": "aave",
      "chain": "ethereum",
      "chainId": 1,
      "market": "0x87870Bca3F3fD6335C3F4ce8392D69350B4fA4E2",
      "symbol": "DAI",
      "underlyingToken": "0x6B175474E89094C44Da98b954EedeAC495271d0F",
      "supplyApy": 0.020050332897814382,
      "borrowApy": 0.038657002911481955,
      "utilization": 0.6978849218498535,
      "tvlUsd": 154851229.16107565,
      "isStable": false,
      "isEthereum": true
    },
    {
      "segment": "evm",
      "protocol": "aave",
      "chain": "ethereum",
      "chainId": 1,
      "market": "0x87870Bca3F3fD6335C3F4ce8392D69350B4fA4E2",
      "symbol": "USDtb",
      "underlyingToken": "0xC139190F447e929f090Edeb554D95AbB8b18aC1C",
      "supplyApy": 0.0061474835988780995,
      "borrowApy": 0.02212270021320087,
      "utilization": 0.3501050035342448,
      "tvlUsd": 197350950.822746,
      "isStable": false,
      "isEthereum": true
    },
    {
      "segment": "evm",
      "protocol": "aave",
      "chain": "ethereum",
      "chainId": 1,
      "market": "0x87870Bca3F3fD6335C3F4ce8392D69350B4fA4E2",
      "symbol": "cbETH",
      "underlyingToken": "0xBe9895146f7AF43049ca1c1AE358B0541Ea49704",
      "supplyApy": 0.0017463147021065653,
      "borrowApy": 0.018029808532937678,
      "utilization": 0.1148744038724615,
      "tvlUsd": 10468905.839290606,
      "isStable": false,
      "isEthereum": true
    },
    {
      "segment": "evm",
      "protocol": "aave",
      "chain": "ethereum",
      "chainId": 1,
      "market": "0x87870Bca3F3fD6335C3F4ce8392D69350B4fA4E2",
      "symbol": "USDS",
      "underlyingToken": "0xdC035D45d973E3EC169d2276DDab16f1e407384F",
      "supplyApy": 0.0011639828899896341,
      "borrowApy": 0.05678253657071462,
      "utilization": 0.028084550285058612,
      "tvlUsd": 39659983.848345384,
      "isStable": false,
      "isEthereum": true
    },
    {
      "segment": "evm",
      "protocol": "aave",
      "chain": "ethereum",
      "chainId": 1,
      "market": "0x87870Bca3F3fD6335C3F4ce8392D69350B4fA4E2",
      "symbol": "LINK",
      "underlyingToken": "0x514910771AF9Ca656af840dff83E8264EcF986CA",
      "supplyApy": 0.00015857535757348291,
      "borrowApy": 0.005568070888856199,
      "utilization": 0.035695453547978144,
      "tvlUsd": 116311509.79810102,
      "isStable": false,
      "isEthereum": true
    },
    {
      "segment": "evm",
      "protocol": "aave",
      "chain": "ethereum",
      "chainId": 1,
      "market": "0x87870Bca3F3fD6335C3F4ce8392D69350B4fA4E2",
      "symbol": "tBTC",
      "underlyingToken": "0x18084fbA666a33d37592fA2633fD49a74DD93a88",
      "supplyApy": 6.218399235052888e-05,
      "borrowApy": 0.0040475610276759656,
      "utilization": 0.030787847515354662,
      "tvlUsd": 122194130.20792982,
      "isStable": false,
      "isEthereum": true
    },
    {
      "segment": "evm",
      "protocol": "aave",
      "chain": "ethereum",
      "chainId": 1,
      "market": "0x87870Bca3F3fD6335C3F4ce8392D69350B4fA4E2",
      "symbol": "WBTC",
      "underlyingToken": "0x2260FAC5E5542a773Aa44fBCfeDf7C193bc2C599",
      "supplyApy": 3.8834464254225755e-05,
      "borrowApy": 0.003252678569344715,
      "utilization": 0.023916796222996365,
      "tvlUsd": 2817897099.3776493,
      "isStable": false,
      "isEthereum": true
    },
    {
      "segment": "evm",
      "protocol": "aave",
      "chain": "ethereum",
      "chainId": 1,
      "market": "0x87870Bca3F3fD6335C3F4ce8392D69350B4fA4E2",
      "symbol": "cbBTC",
      "underlyingToken": "0xcbB7C0000aB88B473b1f5aFd9ef808440eed33Bf",
      "supplyApy": 1.767329887037173e-05,
      "borrowApy": 0.0030795098466637146,
      "utilization": 0.011495558653955016,
      "tvlUsd": 1858621857.6892354,
      "isStable": false,
      "isEthereum": true
    },
    {
      "segment": "evm",
      "protocol": "aave",
      "chain": "ethereum",
      "chainId": 1,
      "market": "0x87870Bca3F3fD6335C3F4ce8392D69350B4fA4E2",
      "symbol": "wstETH",
      "underlyingToken": "0x7f39C581F595B53c5cb19bD0b3f8dA6c935E2Ca0",
      "supplyApy": 1.6833244382684092e-05,
      "borrowApy": 0.0005691201594131873,
      "utilization": 0.045516661919384145,
      "tvlUsd": 3426211598.0045357,
      "isStable": false,
      "isEthereum": true
    },
    {
      "segment": "evm",
      "protocol": "aave",
      "chain": "ethereum",
      "chainId": 1,
      "market": "0x87870Bca3F3fD6335C3F4ce8392D69350B4fA4E2",
      "symbol": "FBTC",
      "underlyingToken": "0xC96dE26018A54D51c097160568752c4E3BD6C364",
      "supplyApy": 3.893262941591169e-06,
      "borrowApy": 0.0051479986677657515,
      "utilization": 0.0015164450045917217,
      "tvlUsd": 39788884.65283643,
      "isStable": false,
      "isEthereum": true
    },
    {
      "segment": "evm",
      "protocol": "aave",
      "chain": "ethereum",
      "chainId": 1,
      "market": "0x87870Bca3F3fD6335C3F4ce8392D69350B4fA4E2",
      "symbol": "weETH",
      "underlyingToken": "0xCd5fE23C85820F7B72D0926FC9b05b43E359b7ee",
      "supplyApy": 9.221604517056062e-07,
      "borrowApy": 0.010089529579135536,
      "utilization": 0.00016701462795642197,
      "tvlUsd": 4841231556.275056,
      "isStable": false,
      "isEthereum": true
    },
    {
      "segment": "evm",
      "protocol": "aave",
      "chain": "ethereum",
      "chainId": 1,
      "market": "0x87870Bca3F3fD6335C3F4ce8392D69350B4fA4E2",
      "symbol": "rETH",
      "underlyingToken": "0xae78736Cd615f374D3085123A210448E74Fc6393",
      "supplyApy": 1.8864934384267955e-07,
      "borrowApy": 0.00018582377463019625,
      "utilization": 0.0011944704591174589,
      "tvlUsd": 81514572.53863887,
      "isStable": false,
      "isEthereum": true
    },
    {
      "segment": "evm",
      "protocol": "aave",
      "chain": "ethereum",
      "chainId": 1,
      "market": "0x87870Bca3F3fD6335C3F4ce8392D69350B4fA4E2",
      "symbol": "rsETH",
      "underlyingToken": "0xA1290d69c65A6Fe4DF752f95823fae25cB99e5A7",
      "supplyApy": 1.3736517491574132e-09,
      "borrowApy": 1.585532194167592e-05,
      "utilization": 0.00010192626162070856,
      "tvlUsd": 913549692.2102344,
      "isStable": false,
      "isEthereum": true
    },
    {
      "segment": "evm",
      "protocol": "aave",
      "chain": "ethereum",
      "chainId": 1,
      "market": "0x87870Bca3F3fD6335C3F4ce8392D69350B4fA4E2",
      "symbol": "osETH",
      "underlyingToken": "0xf1C9acDc66974dFB6dEcB12aA385b9cD01190E38",
      "supplyApy": 3.249563764181262e-12,
      "borrowApy": 7.7116267387657e-07,
      "utilization": 4.957472427498058e-06,
      "tvlUsd": 323114518.9230099,
      "isStable": false,
      "isEthereum": true
    },
    {
      "segment": "evm",
      "protocol": "aave",
      "chain": "ethereum",
      "chainId": 1,
      "market": "0x87870Bca3F3fD6335C3F4ce8392D69350B4fA4E2",
      "symbol": "LBTC",
      "underlyingToken": "0x8236a87084f8B84306f72007F36F2618A5634494",
      "supplyApy": 2.408654715842862e-12,
      "borrowApy": 6.543741805941048e-07,
      "utilization": 7.361702793798196e-06,
      "tvlUsd": 158515821.90155783,
      "isStable": false,
      "isEthereum": true
    },
    {
      "segment": "evm",
      "protocol": "aave",
      "chain": "ethereum",
      "chainId": 1,
      "market": "0x87870Bca3F3fD6335C3F4ce8392D69350B4fA4E2",
      "symbol": "PT-sUSDE-7MAY2026",
      "underlyingToken": "0x3de0ff76E8b528C092d47b9DaC775931cef80F49",
      "supplyApy": 0.0,
      "borrowApy": 0.0,
      "utilization": 0.0,
      "tvlUsd": 316558353.55017936,
      "isStable": false,
      "isEthereum": true
    },
    {
      "segment": "evm",
      "protocol": "aave",
      "chain": "ethereum",
      "chainId": 1,
      "market": "0x87870Bca3F3fD6335C3F4ce8392D69350B4fA4E2",
      "symbol": "GHO",
      "underlyingToken": "0x40D16FC0246aD3160Ccc09B8D0D3A2cD28aE6C2f",
      "supplyApy": 0.0,
      "borrowApy": 0.0356197087795092,
      "utilization": 0.6239465890059926,
      "tvlUsd": 185589684.16936702,
      "isStable": false,
      "isEthereum": true
    },
    {
      "segment": "evm",
      "protocol": "aave",
      "chain": "ethereum",
      "chainId": 1,
      "market": "0x87870Bca3F3fD6335C3F4ce8392D69350B4fA4E2",
      "symbol": "syrupUSDT",
      "underlyingToken": "0x356B8d89c1e1239Cbbb9dE4815c39A1474d5BA7D",
      "supplyApy": 0.0,
      "borrowApy": 0.0,
      "utilization": 0.0,
      "tvlUsd": 167652955.0934742,
      "isStable": false,
      "isEthereum": true
    },
    {
      "segment": "evm",
      "protocol": "aave",
      "chain": "ethereum",
      "chainId": 1,
      "market": "0x87870Bca3F3fD6335C3F4ce8392D69350B4fA4E2",
      "symbol": "XAUt",
      "underlyingToken": "0x68749665FF8D2d112Fa859AA293F07A622782F38",
      "supplyApy": 0.0,
      "borrowApy": 0.0,
      "utilization": 0.0,
      "tvlUsd": 100116116.089643,
      "isStable": false,
      "isEthereum": true
    },
    {
      "segment": "evm",
      "protocol": "aave",
      "chain": "ethereum",
      "chainId": 1,
      "market": "0x87870Bca3F3fD6335C3F4ce8392D69350B4fA4E2",
      "symbol": "PT-srUSDe-2APR2026",
      "underlyingToken": "0x9Bf45ab47747F4B4dD09B3C2c73953484b4eB375",
      "supplyApy": 0.0,
      "borrowApy": 0.0,
      "utilization": 0.0,
      "tvlUsd": 67931830.94066948,
      "isStable": false,
      "isEthereum": true
    },
    {
      "segment": "evm",
      "protocol": "aave",
      "chain": "ethereum",
      "chainId": 1,
      "market": "0x87870Bca3F3fD6335C3F4ce8392D69350B4fA4E2",
      "symbol": "eBTC",
      "underlyingToken": "0x657e8C867D8B37dCC18fA4Caead9C45EB088C642",
      "supplyApy": 0.0,
      "borrowApy": 0.0,
      "utilization": 0.0,
      "tvlUsd": 44938716.58067622,
      "isStable": false,
      "isEthereum": true
    },
    {
      "segment": "evm",
      "protocol": "aave",
      "chain": "ethereum",
      "chainId": 1,
      "market": "0x87870Bca3F3fD6335C3F4ce8392D69350B4fA4E2",
      "symbol": "PT-USDe-7MAY2026",
      "underlyingToken": "0xAeBf0Bb9f57E89260d57f31AF34eB58657d96Ce0",
      "supplyApy": 0.0,
      "borrowApy": 0.0,
      "utilization": 0.0,
      "tvlUsd": 11122273.06496896,
      "isStable": false,
      "isEthereum": true
    },
    {
      "segment": "evm",
      "protocol": "aave",
      "chain": "arbitrum",
      "chainId": 42161,
      "market": "0x794a61358D6845594F94dc1DB02A252b5b4814aD",
      "symbol": "WETH",
      "underlyingToken": "0x82aF49447D8a07e3bd95BD0d56f35241523fBab1",
      "supplyApy": 0.01932688384407628,
      "borrowApy": 0.02504659851349919,
      "utilization": 0.9103611076728334,
      "tvlUsd": 318419224.47618395,
      "isStable": false,
      "isEthereum": false
    },
    {
      "segment": "evm",
      "protocol": "aave",
      "chain": "base",
      "chainId": 8453,
      "market": "0xA238Dd80C259a72e81d7e4664a9801593F98d1c5",
      "symbol": "WETH",
      "underlyingToken": "0x4200000000000000000000000000000000000006",
      "supplyApy": 0.01896459765392261,
      "borrowApy": 0.025087636349162532,
      "utilization": 0.8920118816562698,
      "tvlUsd": 238909204.85369045,
      "isStable": false,
      "isEthereum": false
    },
    {
      "segment": "evm",
      "protocol": "aave",
      "chain": "arbitrum",
      "chainId": 42161,
      "market": "0x794a61358D6845594F94dc1DB02A252b5b4814aD",
      "symbol": "USD\u20ae0",
      "underlyingToken": "0xFd086bC7CD5C481DCC9C85ebE478A1C0b69FCbb9",
      "supplyApy": 0.016084860225873517,
      "borrowApy": 0.031887499661689404,
      "utilization": 0.5650126442978148,
      "tvlUsd": 82875682.46390808,
      "isStable": false,
      "isEthereum": false
    },
    {
      "segment": "evm",
      "protocol": "aave",
      "chain": "base",
      "chainId": 8453,
      "market": "0xA238Dd80C259a72e81d7e4664a9801593F98d1c5",
      "symbol": "EURC",
      "underlyingToken": "0x60a3E35Cc302bFA44Cb288Bc5a4F316Fdb1adb42",
      "supplyApy": 0.005061116175023385,
      "borrowApy": 0.021855773792253466,
      "utilization": 0.2594443553010816,
      "tvlUsd": 22386786.355721038,
      "isStable": false,
      "isEthereum": false
    },
    {
      "segment": "evm",
      "protocol": "aave",
      "chain": "base",
      "chainId": 8453,
      "market": "0xA238Dd80C259a72e81d7e4664a9801593F98d1c5",
      "symbol": "cbETH",
      "underlyingToken": "0x2Ae3F1Ec7F1F5012CFEab0185bfc7aa3cf0DEc22",
      "supplyApy": 0.001520628074433536,
      "borrowApy": 0.016815349057641496,
      "utilization": 0.10719989767939597,
      "tvlUsd": 13097008.55688287,
      "isStable": false,
      "isEthereum": false
    },
    {
      "segment": "evm",
      "protocol": "aave",
      "chain": "arbitrum",
      "chainId": 42161,
      "market": "0x794a61358D6845594F94dc1DB02A252b5b4814aD",
      "symbol": "WBTC",
      "underlyingToken": "0x2f2a2543B76A4166549F7aaB2e75Bef0aefC5B0f",
      "supplyApy": 0.0004102055167782187,
      "borrowApy": 0.009418827436989284,
      "utilization": 0.08749478454057277,
      "tvlUsd": 185875431.89846227,
      "isStable": false,
      "isEthereum": false
    },
    {
      "segment": "evm",
      "protocol": "aave",
      "chain": "base",
      "chainId": 8453,
      "market": "0xA238Dd80C259a72e81d7e4664a9801593F98d1c5",
      "symbol": "cbBTC",
      "underlyingToken": "0xcbB7C0000aB88B473b1f5aFd9ef808440eed33Bf",
      "supplyApy": 0.0002261143956498504,
      "borrowApy": 0.00790311252432996,
      "utilization": 0.05744088058053554,
      "tvlUsd": 166744978.90116385,
      "isStable": false,
      "isEthereum": false
    },
    {
      "segment": "evm",
      "protocol": "aave",
      "chain": "base",
      "chainId": 8453,
      "market": "0xA238Dd80C259a72e81d7e4664a9801593F98d1c5",
      "symbol": "wstETH",
      "underlyingToken": "0xc1CBa3fCea344f92D9239c08C0568f6F2F0ee452",
      "supplyApy": 4.414596652267168e-06,
      "borrowApy": 0.00016853104626723023,
      "utilization": 0.027575484034429464,
      "tvlUsd": 46108084.77545856,
      "isStable": false,
      "isEthereum": false
    },
    {
      "segment": "evm",
      "protocol": "aave",
      "chain": "arbitrum",
      "chainId": 42161,
      "market": "0x794a61358D6845594F94dc1DB02A252b5b4814aD",
      "symbol": "wstETH",
      "underlyingToken": "0x5979D7b546E38E414F7E9822514be443A4800529",
      "supplyApy": 1.685929180876132e-06,
      "borrowApy": 0.00010414546974886397,
      "utilization": 0.017041098599408687,
      "tvlUsd": 77115557.27644065,
      "isStable": false,
      "isEthereum": false
    },
    {
      "segment": "evm",
      "protocol": "aave",
      "chain": "base",
      "chainId": 8453,
      "market": "0xA238Dd80C259a72e81d7e4664a9801593F98d1c5",
      "symbol": "weETH",
      "underlyingToken": "0x04C0599Ae5A44757c0af6F9eC3b93da8976c150A",
      "supplyApy": 3.1447784779953713e-07,
      "borrowApy": 0.01006362480811008,
      "utilization": 5.710170574070928e-05,
      "tvlUsd": 175735321.90531042,
      "isStable": false,
      "isEthereum": false
    },
    {
      "segment": "evm",
      "protocol": "aave",
      "chain": "arbitrum",
      "chainId": 42161,
      "market": "0x794a61358D6845594F94dc1DB02A252b5b4814aD",
      "symbol": "weETH",
      "underlyingToken": "0x35751007a407ca6FEFfE80b3cB397736D2cf4dbe",
      "supplyApy": 1.7214951299292102e-07,
      "borrowApy": 0.010057538441424676,
      "utilization": 3.127711404131252e-05,
      "tvlUsd": 139929096.02768505,
      "isStable": false,
      "isEthereum": false
    },
    {
      "segment": "evm",
      "protocol": "aave",
      "chain": "base",
      "chainId": 8453,
      "market": "0xA238Dd80C259a72e81d7e4664a9801593F98d1c5",
      "symbol": "syrupUSDC",
      "underlyingToken": "0x660975730059246A68521a3e2FBD4740173100f5",
      "supplyApy": 0.0,
      "borrowApy": 0.0,
      "utilization": 0.0,
      "tvlUsd": 191742594.80522984,
      "isStable": false,
      "isEthereum": false
    },
    {
      "segment": "evm",
      "protocol": "aave",
      "chain": "arbitrum",
      "chainId": 42161,
      "market": "0x794a61358D6845594F94dc1DB02A252b5b4814aD",
      "symbol": "rsETH",
      "underlyingToken": "0x4186BFC76E2E237523CBC30FD220FE055156b41F",
      "supplyApy": 0.0,
      "borrowApy": 0.0,
      "utilization": 0.0,
      "tvlUsd": 82636503.41297394,
      "isStable": false,
      "isEthereum": false
    },
    {
      "segment": "evm",
      "protocol": "aave",
      "chain": "arbitrum",
      "chainId": 42161,
      "market": "0x794a61358D6845594F94dc1DB02A252b5b4814aD",
      "symbol": "ezETH",
      "underlyingToken": "0x2416092f143378750bb29b79eD961ab195CcEea5",
      "supplyApy": 0.0,
      "borrowApy": 0.0,
      "utilization": 0.0,
      "tvlUsd": 80238306.75911048,
      "isStable": false,
      "isEthereum": false
    },
    {
      "segment": "evm",
      "protocol": "aave",
      "chain": "base",
      "chainId": 8453,
      "market": "0xA238Dd80C259a72e81d7e4664a9801593F98d1c5",
      "symbol": "wrsETH",
      "underlyingToken": "0xEDfa23602D0EC14714057867A78d01e94176BEA0",
      "supplyApy": 0.0,
      "borrowApy": 0.010050167082566633,
      "utilization": 0.0,
      "tvlUsd": 52825244.15497632,
      "isStable": false,
      "isEthereum": false
    }
  ],
  "counts": {
    "reserves": 98,
    "skipped_nulls": 6,
    "skipped_small": 45,
    "kept": 47
  },
  "minTvlUsd": 10000000.0
}
