{
  "updatedAt": "2026-02-26T18:05:32.339284+00:00",
  "markets": [
    {
      "segment": "evm",
      "protocol": "aave",
      "chain": "ethereum",
      "chainId": 1,
      "market": "0x87870Bca3F3fD6335C3F4ce8392D69350B4fA4E2",
      "symbol": "USDe",
      "underlyingToken": "0x4c9EDD5852cd905f086C759E8383e09bff1E68B3",
      "supplyApy": 0.008434493552151454,
      "borrowApy": 0.02588848341725582,
      "utilization": 0.43815520791938684,
      "tvlUsd": 1074749606.0126064,
      "isStable": true,
      "isEthereum": true
    },
    {
      "segment": "evm",
      "protocol": "aave",
      "chain": "ethereum",
      "chainId": 1,
      "market": "0x87870Bca3F3fD6335C3F4ce8392D69350B4fA4E2",
      "symbol": "PYUSD",
      "underlyingToken": "0x6c3ea9036406852006290770BEdFcAbA0e23A0e8",
      "supplyApy": 0.01667678495827673,
      "borrowApy": 0.0324681286996848,
      "utilization": 0.5751398395708924,
      "tvlUsd": 448422233.91468644,
      "isStable": true,
      "isEthereum": true
    },
    {
      "segment": "evm",
      "protocol": "aave",
      "chain": "ethereum",
      "chainId": 1,
      "market": "0x87870Bca3F3fD6335C3F4ce8392D69350B4fA4E2",
      "symbol": "USDT",
      "underlyingToken": "0xdAC17F958D2ee523a2206206994597C13D831ec7",
      "supplyApy": 0.019094523330136743,
      "borrowApy": 0.034373772362492866,
      "utilization": 0.6218498409844713,
      "tvlUsd": 5685475659.109933,
      "isStable": true,
      "isEthereum": true
    },
    {
      "segment": "evm",
      "protocol": "aave",
      "chain": "ethereum",
      "chainId": 1,
      "market": "0x87870Bca3F3fD6335C3F4ce8392D69350B4fA4E2",
      "symbol": "RLUSD",
      "underlyingToken": "0x8292Bb45bf1Ee4d140127049757C2E0fF06317eD",
      "supplyApy": 0.008801363951903871,
      "borrowApy": 0.03544181884570137,
      "utilization": 0.31450302228453153,
      "tvlUsd": 611073370.637258,
      "isStable": true,
      "isEthereum": true
    },
    {
      "segment": "evm",
      "protocol": "aave",
      "chain": "ethereum",
      "chainId": 1,
      "market": "0x87870Bca3F3fD6335C3F4ce8392D69350B4fA4E2",
      "symbol": "USDC",
      "underlyingToken": "0xA0b86991c6218b36c1d19D4a2e9Eb0cE3606eB48",
      "supplyApy": 0.020500291357513446,
      "borrowApy": 0.0356261918836428,
      "utilization": 0.6441141340110333,
      "tvlUsd": 3867935186.369124,
      "isStable": true,
      "isEthereum": true
    },
    {
      "segment": "evm",
      "protocol": "aave",
      "chain": "ethereum",
      "chainId": 1,
      "market": "0x87870Bca3F3fD6335C3F4ce8392D69350B4fA4E2",
      "symbol": "USDG",
      "underlyingToken": "0xe343167631d89B6Ffc58B88d6b7fB0228795491D",
      "supplyApy": 0.037749866920534565,
      "borrowApy": 0.060711254143774505,
      "utilization": 0.7858641373330233,
      "tvlUsd": 53292944.927734,
      "isStable": true,
      "isEthereum": true
    },
    {
      "segment": "evm",
      "protocol": "aave",
      "chain": "arbitrum",
      "chainId": 42161,
      "market": "0x794a61358D6845594F94dc1DB02A252b5b4814aD",
      "symbol": "USDC",
      "underlyingToken": "0xaf88d065e77c8cC2239327C5EDb3A432268e5831",
      "supplyApy": 0.015114687191154767,
      "borrowApy": 0.03089842262136759,
      "utilization": 0.5477521465975037,
      "tvlUsd": 285376618.04391485,
      "isStable": true,
      "isEthereum": false
    },
    {
      "segment": "evm",
      "protocol": "aave",
      "chain": "base",
      "chainId": 8453,
      "market": "0xA238Dd80C259a72e81d7e4664a9801593F98d1c5",
      "symbol": "USDC",
      "underlyingToken": "0x833589fCD6eDb6E08f4c7C32D4f71b54bdA02913",
      "supplyApy": 0.03330981677386797,
      "borrowApy": 0.04600063776984015,
      "utilization": 0.8095311103842514,
      "tvlUsd": 398989418.92724735,
      "isStable": true,
      "isEthereum": false
    },
    {
      "segment": "evm",
      "protocol": "aave",
      "chain": "ethereum",
      "chainId": 1,
      "market": "0x87870Bca3F3fD6335C3F4ce8392D69350B4fA4E2",
      "symbol": "EURC",
      "underlyingToken": "0x1aBaEA1f7C830bD89Acc67eC4af516284b1bC33c",
      "supplyApy": 0.022894383001823965,
      "borrowApy": 0.03998361285547177,
      "utilization": 0.6415356832376286,
      "tvlUsd": 95077443.58137226,
      "isStable": false,
      "isEthereum": true
    },
    {
      "segment": "evm",
      "protocol": "aave",
      "chain": "ethereum",
      "chainId": 1,
      "market": "0x87870Bca3F3fD6335C3F4ce8392D69350B4fA4E2",
      "symbol": "DAI",
      "underlyingToken": "0x6B175474E89094C44Da98b954EedeAC495271d0F",
      "supplyApy": 0.020371833751298325,
      "borrowApy": 0.03896849813400511,
      "utilization": 0.7034026461074727,
      "tvlUsd": 153883740.96502393,
      "isStable": false,
      "isEthereum": true
    },
    {
      "segment": "evm",
      "protocol": "aave",
      "chain": "ethereum",
      "chainId": 1,
      "market": "0x87870Bca3F3fD6335C3F4ce8392D69350B4fA4E2",
      "symbol": "WETH",
      "underlyingToken": "0xC02aaA39b223FE8D0A0e5C4F27eAD9083C756Cc2",
      "supplyApy": 0.019655526157186808,
      "borrowApy": 0.024731568099917067,
      "utilization": 0.9373408925703217,
      "tvlUsd": 5790721813.537668,
      "isStable": false,
      "isEthereum": true
    },
    {
      "segment": "evm",
      "protocol": "aave",
      "chain": "ethereum",
      "chainId": 1,
      "market": "0x87870Bca3F3fD6335C3F4ce8392D69350B4fA4E2",
      "symbol": "USDtb",
      "underlyingToken": "0xC139190F447e929f090Edeb554D95AbB8b18aC1C",
      "supplyApy": 0.006208540654709235,
      "borrowApy": 0.022233158565129023,
      "utilization": 0.35183385534736705,
      "tvlUsd": 196819371.87409845,
      "isStable": false,
      "isEthereum": true
    },
    {
      "segment": "evm",
      "protocol": "aave",
      "chain": "ethereum",
      "chainId": 1,
      "market": "0x87870Bca3F3fD6335C3F4ce8392D69350B4fA4E2",
      "symbol": "cbETH",
      "underlyingToken": "0xBe9895146f7AF43049ca1c1AE358B0541Ea49704",
      "supplyApy": 0.0017466238540442508,
      "borrowApy": 0.01803141727827973,
      "utilization": 0.11488511898201424,
      "tvlUsd": 10009649.032511096,
      "isStable": false,
      "isEthereum": true
    },
    {
      "segment": "evm",
      "protocol": "aave",
      "chain": "ethereum",
      "chainId": 1,
      "market": "0x87870Bca3F3fD6335C3F4ce8392D69350B4fA4E2",
      "symbol": "USDS",
      "underlyingToken": "0xdC035D45d973E3EC169d2276DDab16f1e407384F",
      "supplyApy": 0.0011616960502728799,
      "borrowApy": 0.05678206345344182,
      "utilization": 0.028029656947369547,
      "tvlUsd": 39742418.8690512,
      "isStable": false,
      "isEthereum": true
    },
    {
      "segment": "evm",
      "protocol": "aave",
      "chain": "ethereum",
      "chainId": 1,
      "market": "0x87870Bca3F3fD6335C3F4ce8392D69350B4fA4E2",
      "symbol": "LINK",
      "underlyingToken": "0x514910771AF9Ca656af840dff83E8264EcF986CA",
      "supplyApy": 0.00018650307305433653,
      "borrowApy": 0.006039887243261567,
      "utilization": 0.03871105577073512,
      "tvlUsd": 109645467.87564678,
      "isStable": false,
      "isEthereum": true
    },
    {
      "segment": "evm",
      "protocol": "aave",
      "chain": "ethereum",
      "chainId": 1,
      "market": "0x87870Bca3F3fD6335C3F4ce8392D69350B4fA4E2",
      "symbol": "tBTC",
      "underlyingToken": "0x18084fbA666a33d37592fA2633fD49a74DD93a88",
      "supplyApy": 6.212251508830083e-05,
      "borrowApy": 0.0040464544347413285,
      "utilization": 0.030765814717074392,
      "tvlUsd": 119300795.69638602,
      "isStable": false,
      "isEthereum": true
    },
    {
      "segment": "evm",
      "protocol": "aave",
      "chain": "ethereum",
      "chainId": 1,
      "market": "0x87870Bca3F3fD6335C3F4ce8392D69350B4fA4E2",
      "symbol": "WBTC",
      "underlyingToken": "0x2260FAC5E5542a773Aa44fBCfeDf7C193bc2C599",
      "supplyApy": 3.909257098987329e-05,
      "borrowApy": 0.0032567256352358446,
      "utilization": 0.024045882429855104,
      "tvlUsd": 2746063200.3980327,
      "isStable": false,
      "isEthereum": true
    },
    {
      "segment": "evm",
      "protocol": "aave",
      "chain": "ethereum",
      "chainId": 1,
      "market": "0x87870Bca3F3fD6335C3F4ce8392D69350B4fA4E2",
      "symbol": "cbBTC",
      "underlyingToken": "0xcbB7C0000aB88B473b1f5aFd9ef808440eed33Bf",
      "supplyApy": 1.8444432597894936e-05,
      "borrowApy": 0.0031005829735411107,
      "utilization": 0.011915722868677954,
      "tvlUsd": 1750379822.1135952,
      "isStable": false,
      "isEthereum": true
    },
    {
      "segment": "evm",
      "protocol": "aave",
      "chain": "ethereum",
      "chainId": 1,
      "market": "0x87870Bca3F3fD6335C3F4ce8392D69350B4fA4E2",
      "symbol": "wstETH",
      "underlyingToken": "0x7f39C581F595B53c5cb19bD0b3f8dA6c935E2Ca0",
      "supplyApy": 1.6906271571270094e-05,
      "borrowApy": 0.0005703536635570907,
      "utilization": 0.045615286017693435,
      "tvlUsd": 3269178112.1064005,
      "isStable": false,
      "isEthereum": true
    },
    {
      "segment": "evm",
      "protocol": "aave",
      "chain": "ethereum",
      "chainId": 1,
      "market": "0x87870Bca3F3fD6335C3F4ce8392D69350B4fA4E2",
      "symbol": "FBTC",
      "underlyingToken": "0xC96dE26018A54D51c097160568752c4E3BD6C364",
      "supplyApy": 3.893262941591169e-06,
      "borrowApy": 0.0051479986677657515,
      "utilization": 0.0015164618808153154,
      "tvlUsd": 38818616.5998034,
      "isStable": false,
      "isEthereum": true
    },
    {
      "segment": "evm",
      "protocol": "aave",
      "chain": "ethereum",
      "chainId": 1,
      "market": "0x87870Bca3F3fD6335C3F4ce8392D69350B4fA4E2",
      "symbol": "weETH",
      "underlyingToken": "0xCd5fE23C85820F7B72D0926FC9b05b43E359b7ee",
      "supplyApy": 9.218297639412894e-07,
      "borrowApy": 0.010089515517996172,
      "utilization": 0.00016695496743799427,
      "tvlUsd": 4634327869.706317,
      "isStable": false,
      "isEthereum": true
    },
    {
      "segment": "evm",
      "protocol": "aave",
      "chain": "ethereum",
      "chainId": 1,
      "market": "0x87870Bca3F3fD6335C3F4ce8392D69350B4fA4E2",
      "symbol": "rETH",
      "underlyingToken": "0xae78736Cd615f374D3085123A210448E74Fc6393",
      "supplyApy": 1.8864934384267955e-07,
      "borrowApy": 0.00018582377463019625,
      "utilization": 0.0011944709403699945,
      "tvlUsd": 77942111.94281267,
      "isStable": false,
      "isEthereum": true
    },
    {
      "segment": "evm",
      "protocol": "aave",
      "chain": "ethereum",
      "chainId": 1,
      "market": "0x87870Bca3F3fD6335C3F4ce8392D69350B4fA4E2",
      "symbol": "rsETH",
      "underlyingToken": "0xA1290d69c65A6Fe4DF752f95823fae25cB99e5A7",
      "supplyApy": 1.4287191183265843e-09,
      "borrowApy": 1.6170008175650298e-05,
      "utilization": 0.00010394921256170477,
      "tvlUsd": 856553280.9902525,
      "isStable": false,
      "isEthereum": true
    },
    {
      "segment": "evm",
      "protocol": "aave",
      "chain": "ethereum",
      "chainId": 1,
      "market": "0x87870Bca3F3fD6335C3F4ce8392D69350B4fA4E2",
      "symbol": "osETH",
      "underlyingToken": "0xf1C9acDc66974dFB6dEcB12aA385b9cD01190E38",
      "supplyApy": 3.249641216597262e-12,
      "borrowApy": 7.711718638913413e-07,
      "utilization": 4.957531501452554e-06,
      "tvlUsd": 308948381.9431468,
      "isStable": false,
      "isEthereum": true
    },
    {
      "segment": "evm",
      "protocol": "aave",
      "chain": "ethereum",
      "chainId": 1,
      "market": "0x87870Bca3F3fD6335C3F4ce8392D69350B4fA4E2",
      "symbol": "LBTC",
      "underlyingToken": "0x8236a87084f8B84306f72007F36F2618A5634494",
      "supplyApy": 2.408595995810861e-12,
      "borrowApy": 6.543662042419219e-07,
      "utilization": 7.361613059947795e-06,
      "tvlUsd": 154652231.92560023,
      "isStable": false,
      "isEthereum": true
    },
    {
      "segment": "evm",
      "protocol": "aave",
      "chain": "ethereum",
      "chainId": 1,
      "market": "0x87870Bca3F3fD6335C3F4ce8392D69350B4fA4E2",
      "symbol": "PT-sUSDE-7MAY2026",
      "underlyingToken": "0x3de0ff76E8b528C092d47b9DaC775931cef80F49",
      "supplyApy": 0.0,
      "borrowApy": 0.0,
      "utilization": 0.0,
      "tvlUsd": 316596321.02444226,
      "isStable": false,
      "isEthereum": true
    },
    {
      "segment": "evm",
      "protocol": "aave",
      "chain": "ethereum",
      "chainId": 1,
      "market": "0x87870Bca3F3fD6335C3F4ce8392D69350B4fA4E2",
      "symbol": "GHO",
      "underlyingToken": "0x40D16FC0246aD3160Ccc09B8D0D3A2cD28aE6C2f",
      "supplyApy": 0.0,
      "borrowApy": 0.0356197087795092,
      "utilization": 0.6865946135007065,
      "tvlUsd": 185598727.1458176,
      "isStable": false,
      "isEthereum": true
    },
    {
      "segment": "evm",
      "protocol": "aave",
      "chain": "ethereum",
      "chainId": 1,
      "market": "0x87870Bca3F3fD6335C3F4ce8392D69350B4fA4E2",
      "symbol": "syrupUSDT",
      "underlyingToken": "0x356B8d89c1e1239Cbbb9dE4815c39A1474d5BA7D",
      "supplyApy": 0.0,
      "borrowApy": 0.0,
      "utilization": 0.0,
      "tvlUsd": 167669631.0,
      "isStable": false,
      "isEthereum": true
    },
    {
      "segment": "evm",
      "protocol": "aave",
      "chain": "ethereum",
      "chainId": 1,
      "market": "0x87870Bca3F3fD6335C3F4ce8392D69350B4fA4E2",
      "symbol": "XAUt",
      "underlyingToken": "0x68749665FF8D2d112Fa859AA293F07A622782F38",
      "supplyApy": 0.0,
      "borrowApy": 0.0,
      "utilization": 0.0,
      "tvlUsd": 100255684.70313784,
      "isStable": false,
      "isEthereum": true
    },
    {
      "segment": "evm",
      "protocol": "aave",
      "chain": "ethereum",
      "chainId": 1,
      "market": "0x87870Bca3F3fD6335C3F4ce8392D69350B4fA4E2",
      "symbol": "PT-srUSDe-2APR2026",
      "underlyingToken": "0x9Bf45ab47747F4B4dD09B3C2c73953484b4eB375",
      "supplyApy": 0.0,
      "borrowApy": 0.0,
      "utilization": 0.0,
      "tvlUsd": 68261384.06736812,
      "isStable": false,
      "isEthereum": true
    },
    {
      "segment": "evm",
      "protocol": "aave",
      "chain": "ethereum",
      "chainId": 1,
      "market": "0x87870Bca3F3fD6335C3F4ce8392D69350B4fA4E2",
      "symbol": "eBTC",
      "underlyingToken": "0x657e8C867D8B37dCC18fA4Caead9C45EB088C642",
      "supplyApy": 0.0,
      "borrowApy": 0.0,
      "utilization": 0.0,
      "tvlUsd": 43842867.05115235,
      "isStable": false,
      "isEthereum": true
    },
    {
      "segment": "evm",
      "protocol": "aave",
      "chain": "ethereum",
      "chainId": 1,
      "market": "0x87870Bca3F3fD6335C3F4ce8392D69350B4fA4E2",
      "symbol": "PT-USDe-7MAY2026",
      "underlyingToken": "0xAeBf0Bb9f57E89260d57f31AF34eB58657d96Ce0",
      "supplyApy": 0.0,
      "borrowApy": 0.0,
      "utilization": 0.0,
      "tvlUsd": 11123234.003796497,
      "isStable": false,
      "isEthereum": true
    },
    {
      "segment": "evm",
      "protocol": "aave",
      "chain": "arbitrum",
      "chainId": 42161,
      "market": "0x794a61358D6845594F94dc1DB02A252b5b4814aD",
      "symbol": "WETH",
      "underlyingToken": "0x82aF49447D8a07e3bd95BD0d56f35241523fBab1",
      "supplyApy": 0.01964634938384907,
      "borrowApy": 0.02525332722804415,
      "utilization": 0.9177820862706471,
      "tvlUsd": 302085936.9282535,
      "isStable": false,
      "isEthereum": false
    },
    {
      "segment": "evm",
      "protocol": "aave",
      "chain": "base",
      "chainId": 8453,
      "market": "0xA238Dd80C259a72e81d7e4664a9801593F98d1c5",
      "symbol": "WETH",
      "underlyingToken": "0x4200000000000000000000000000000000000006",
      "supplyApy": 0.019183178153728976,
      "borrowApy": 0.025232228100173296,
      "utilization": 0.897089433833552,
      "tvlUsd": 226987834.31204608,
      "isStable": false,
      "isEthereum": false
    },
    {
      "segment": "evm",
      "protocol": "aave",
      "chain": "arbitrum",
      "chainId": 42161,
      "market": "0x794a61358D6845594F94dc1DB02A252b5b4814aD",
      "symbol": "USD\u20ae0",
      "underlyingToken": "0xFd086bC7CD5C481DCC9C85ebE478A1C0b69FCbb9",
      "supplyApy": 0.017422490261276725,
      "borrowApy": 0.03319712857941904,
      "utilization": 0.5878429734451673,
      "tvlUsd": 82958894.725198,
      "isStable": false,
      "isEthereum": false
    },
    {
      "segment": "evm",
      "protocol": "aave",
      "chain": "base",
      "chainId": 8453,
      "market": "0xA238Dd80C259a72e81d7e4664a9801593F98d1c5",
      "symbol": "EURC",
      "underlyingToken": "0x60a3E35Cc302bFA44Cb288Bc5a4F316Fdb1adb42",
      "supplyApy": 0.005042036707110468,
      "borrowApy": 0.021814197012294232,
      "utilization": 0.2589561979466668,
      "tvlUsd": 22433559.077017702,
      "isStable": false,
      "isEthereum": false
    },
    {
      "segment": "evm",
      "protocol": "aave",
      "chain": "base",
      "chainId": 8453,
      "market": "0xA238Dd80C259a72e81d7e4664a9801593F98d1c5",
      "symbol": "cbETH",
      "underlyingToken": "0x2Ae3F1Ec7F1F5012CFEab0185bfc7aa3cf0DEc22",
      "supplyApy": 0.0017494875806323797,
      "borrowApy": 0.01804631276816199,
      "utilization": 0.11497770756075029,
      "tvlUsd": 12293642.24396566,
      "isStable": false,
      "isEthereum": false
    },
    {
      "segment": "evm",
      "protocol": "aave",
      "chain": "arbitrum",
      "chainId": 42161,
      "market": "0x794a61358D6845594F94dc1DB02A252b5b4814aD",
      "symbol": "WBTC",
      "underlyingToken": "0x2f2a2543B76A4166549F7aaB2e75Bef0aefC5B0f",
      "supplyApy": 0.0004150190733994351,
      "borrowApy": 0.009454062746397483,
      "utilization": 0.08819290028602109,
      "tvlUsd": 181936864.74193034,
      "isStable": false,
      "isEthereum": false
    },
    {
      "segment": "evm",
      "protocol": "aave",
      "chain": "base",
      "chainId": 8453,
      "market": "0xA238Dd80C259a72e81d7e4664a9801593F98d1c5",
      "symbol": "cbBTC",
      "underlyingToken": "0xcbB7C0000aB88B473b1f5aFd9ef808440eed33Bf",
      "supplyApy": 0.00022656836052734313,
      "borrowApy": 0.007907368540386131,
      "utilization": 0.05752533476760059,
      "tvlUsd": 163338980.4576113,
      "isStable": false,
      "isEthereum": false
    },
    {
      "segment": "evm",
      "protocol": "aave",
      "chain": "base",
      "chainId": 8453,
      "market": "0xA238Dd80C259a72e81d7e4664a9801593F98d1c5",
      "symbol": "wstETH",
      "underlyingToken": "0xc1CBa3fCea344f92D9239c08C0568f6F2F0ee452",
      "supplyApy": 4.468574508023174e-06,
      "borrowApy": 0.00016955832636564357,
      "utilization": 0.02774355597214272,
      "tvlUsd": 42245649.49720396,
      "isStable": false,
      "isEthereum": false
    },
    {
      "segment": "evm",
      "protocol": "aave",
      "chain": "arbitrum",
      "chainId": 42161,
      "market": "0x794a61358D6845594F94dc1DB02A252b5b4814aD",
      "symbol": "wstETH",
      "underlyingToken": "0x5979D7b546E38E414F7E9822514be443A4800529",
      "supplyApy": 1.6952881857592826e-06,
      "borrowApy": 0.00010443415299497163,
      "utilization": 0.017088332838213354,
      "tvlUsd": 72814035.79058719,
      "isStable": false,
      "isEthereum": false
    },
    {
      "segment": "evm",
      "protocol": "aave",
      "chain": "base",
      "chainId": 8453,
      "market": "0xA238Dd80C259a72e81d7e4664a9801593F98d1c5",
      "symbol": "weETH",
      "underlyingToken": "0x04C0599Ae5A44757c0af6F9eC3b93da8976c150A",
      "supplyApy": 3.146732833130739e-07,
      "borrowApy": 0.01006363316048678,
      "utilization": 5.713714053372107e-05,
      "tvlUsd": 167993817.05241168,
      "isStable": false,
      "isEthereum": false
    },
    {
      "segment": "evm",
      "protocol": "aave",
      "chain": "arbitrum",
      "chainId": 42161,
      "market": "0x794a61358D6845594F94dc1DB02A252b5b4814aD",
      "symbol": "weETH",
      "underlyingToken": "0x35751007a407ca6FEFfE80b3cB397736D2cf4dbe",
      "supplyApy": 1.7218027811618184e-07,
      "borrowApy": 0.010057539757816892,
      "utilization": 3.128271211848395e-05,
      "tvlUsd": 133973858.44422306,
      "isStable": false,
      "isEthereum": false
    },
    {
      "segment": "evm",
      "protocol": "aave",
      "chain": "base",
      "chainId": 8453,
      "market": "0xA238Dd80C259a72e81d7e4664a9801593F98d1c5",
      "symbol": "syrupUSDC",
      "underlyingToken": "0x660975730059246A68521a3e2FBD4740173100f5",
      "supplyApy": 0.0,
      "borrowApy": 0.0,
      "utilization": 0.0,
      "tvlUsd": 191766629.42993265,
      "isStable": false,
      "isEthereum": false
    },
    {
      "segment": "evm",
      "protocol": "aave",
      "chain": "arbitrum",
      "chainId": 42161,
      "market": "0x794a61358D6845594F94dc1DB02A252b5b4814aD",
      "symbol": "rsETH",
      "underlyingToken": "0x4186BFC76E2E237523CBC30FD220FE055156b41F",
      "supplyApy": 0.0,
      "borrowApy": 0.0,
      "utilization": 0.0,
      "tvlUsd": 79135749.98488824,
      "isStable": false,
      "isEthereum": false
    },
    {
      "segment": "evm",
      "protocol": "aave",
      "chain": "arbitrum",
      "chainId": 42161,
      "market": "0x794a61358D6845594F94dc1DB02A252b5b4814aD",
      "symbol": "ezETH",
      "underlyingToken": "0x2416092f143378750bb29b79eD961ab195CcEea5",
      "supplyApy": 0.0,
      "borrowApy": 0.0,
      "utilization": 0.0,
      "tvlUsd": 76842722.3927066,
      "isStable": false,
      "isEthereum": false
    },
    {
      "segment": "evm",
      "protocol": "aave",
      "chain": "base",
      "chainId": 8453,
      "market": "0xA238Dd80C259a72e81d7e4664a9801593F98d1c5",
      "symbol": "wrsETH",
      "underlyingToken": "0xEDfa23602D0EC14714057867A78d01e94176BEA0",
      "supplyApy": 0.0,
      "borrowApy": 0.010050167082566633,
      "utilization": 0.0,
      "tvlUsd": 50535389.016708255,
      "isStable": false,
      "isEthereum": false
    }
  ],
  "counts": {
    "reserves": 98,
    "skipped_nulls": 6,
    "skipped_small": 45,
    "kept": 47
  },
  "minTvlUsd": 10000000.0
}
